{
  "unpublishedPage": {
    "name": "login",
    "slug": "login",
    "layouts": [
      {
        "viewMode": false,
        "dsl": {
          "widgetName": "MainContainer",
          "backgroundColor": "none",
          "rightColumn": 4896,
          "snapColumns": 64,
          "detachFromLayout": true,
          "widgetId": "0",
          "topRow": 0,
          "bottomRow": 1292,
          "containerStyle": "none",
          "snapRows": 124,
          "parentRowSpace": 1,
          "type": "CANVAS_WIDGET",
          "canExtend": true,
          "version": 85,
          "minHeight": 1292,
          "dynamicTriggerPathList": [],
          "parentColumnSpace": 1,
          "dynamicBindingPathList": [],
          "leftColumn": 0
        },
        "layoutOnLoadActions": [
          [
            {
              "id": "login_authentication.verifyAuth",
              "name": "authentication.verifyAuth",
              "collectionId": "login_authentication",
              "confirmBeforeExecute": false,
              "pluginType": "JS",
              "jsonPathKeys": [
                "async function () {\n  const current_user = appsmith.store.current_user;\n  if (!_.isEmpty(current_user)) {\n    navigateTo('applications');\n  }\n}"
              ],
              "timeoutInMillisecond": 10000
            }
          ]
        ],
        "layoutOnLoadActionErrors": [],
        "validOnPageLoadActions": true,
        "id": "login",
        "deleted": false,
        "policies": [],
        "userPermissions": []
      }
    ],
    "userPermissions": [],
    "policies": [],
    "isHidden": false
  },
  "deleted": false,
  "gitSyncId": "64f5b709d9cec14b5ad582d5_64f5b709d9cec14b5ad582d7"
}